{
    "name": "ChageEffect",
    "particles": [
        {
            "blendMode": 2,
            "colorMode": 2,
            "colorVariation": 0.10000000149011612,
            "emitType": 2,
            "emitters": [
                {
                    "count": 2,
                    "frequency": 0.2199999988079071,
                    "rotationParm": {
                        "initialRotation": [
                            0.0,
                            0.0,
                            0.0
                        ],
                        "randomizeInitialRotation": true,
                        "rotateContinuously": true,
                        "rotationSpeed": [
                            0.0,
                            0.0,
                            0.0
                        ],
                        "useRotation": true
                    },
                    "shape": 1,
                    "transform": {
                        "rotate": [
                            0.0,
                            0.0,
                            0.0
                        ],
                        "scale": [
                            1.0,
                            1.0,
                            1.0
                        ],
                        "translate": [
                            0.0,
                            0.0,
                            0.0
                        ]
                    }
                }
            ],
            "fixedMaxScale": [
                1.0,
                1.0,
                1.0
            ],
            "flyToEmitter": true,
            "isBillboard": true,
            "isComplement": false,
            "isRandomLifeTime": false,
            "isStatic": false,
            "lifeTime": 0.7509999871253967,
            "maxLifeTime": 0.699999988079071,
            "minLifeTime": 0.5,
            "model": "plane.obj",
            "name": "",
            "randomScaleMax": [
                0.699999988079071,
                0.4000000059604645,
                6.0
            ],
            "randomScaleMin": [
                0.6600000262260437,
                0.3799999952316284,
                1.0
            ],
            "scaleMode": 0,
            "selectedColor": [
                0.92277991771698,
                0.08550853282213211,
                0.0,
                1.0
            ],
            "texture": "particle.png",
            "useRandomScale": true,
            "useRotation": false
        },
        {
            "blendMode": 2,
            "colorMode": 1,
            "colorVariation": 0.10000000149011612,
            "emitType": 2,
            "emitters": [
                {
                    "count": 2,
                    "frequency": 1.5,
                    "rotationParm": {
                        "initialRotation": [
                            0.0,
                            0.0,
                            0.0
                        ],
                        "randomizeInitialRotation": true,
                        "rotateContinuously": false,
                        "rotationSpeed": [
                            0.0,
                            0.0,
                            0.0
                        ],
                        "useRotation": true
                    },
                    "shape": 1,
                    "transform": {
                        "rotate": [
                            0.0,
                            0.0,
                            0.0
                        ],
                        "scale": [
                            1.0,
                            1.0,
                            1.0
                        ],
                        "translate": [
                            0.0,
                            0.0,
                            0.0
                        ]
                    }
                }
            ],
            "fixedMaxScale": [
                1.0,
                1.0,
                1.0
            ],
            "flyToEmitter": false,
            "isBillboard": true,
            "isComplement": false,
            "isRandomLifeTime": false,
            "isStatic": true,
            "lifeTime": 1.0770000219345093,
            "maxLifeTime": 0.8600000143051147,
            "minLifeTime": 0.7200000286102295,
            "model": "plane.obj",
            "name": "",
            "randomScaleMax": [
                5.28000020980835,
                0.07999999821186066,
                6.0
            ],
            "randomScaleMin": [
                3.4800000190734863,
                0.07999999821186066,
                1.0
            ],
            "scaleMode": 0,
            "selectedColor": [
                0.8416988253593445,
                0.1624901294708252,
                0.1624901294708252,
                1.0
            ],
            "texture": "particle.png",
            "useRandomScale": true,
            "useRotation": false
        },
        {
            "blendMode": 2,
            "colorMode": 1,
            "colorVariation": 0.10000000149011612,
            "emitType": 1,
            "emitters": [
                {
                    "count": 1,
                    "frequency": 1.9600000381469727,
                    "rotationParm": {
                        "initialRotation": [
                            0.0,
                            0.0,
                            0.0
                        ],
                        "randomizeInitialRotation": true,
                        "rotateContinuously": false,
                        "rotationSpeed": [
                            0.0,
                            0.0,
                            0.0
                        ],
                        "useRotation": true
                    },
                    "shape": 1,
                    "transform": {
                        "rotate": [
                            0.0,
                            0.0,
                            0.0
                        ],
                        "scale": [
                            1.0,
                            1.0,
                            1.0
                        ],
                        "translate": [
                            0.0,
                            0.0,
                            0.0
                        ]
                    }
                }
            ],
            "fixedMaxScale": [
                1.0,
                1.0,
                1.0
            ],
            "flyToEmitter": false,
            "isBillboard": true,
            "isComplement": false,
            "isRandomLifeTime": true,
            "isStatic": true,
            "lifeTime": 3.6058030128479004,
            "maxLifeTime": 3.680000066757202,
            "minLifeTime": 3.5999999046325684,
            "model": "plane.obj",
            "name": "",
            "randomScaleMax": [
                4.0,
                4.0,
                6.0
            ],
            "randomScaleMin": [
                4.0,
                4.0,
                1.0
            ],
            "scaleMode": 3,
            "selectedColor": [
                0.6447876691818237,
                0.13941355049610138,
                0.13941355049610138,
                1.0
            ],
            "texture": "redCircle.png",
            "useRandomScale": true,
            "useRotation": false
        }
    ]
}